abstract_blockchain/__init__.py
abstract_blockchain/abstract_abis.py
abstract_blockchain/abstract_accounts.py
abstract_blockchain/abstract_api_gui.py
abstract_blockchain/abstract_apis.py
abstract_blockchain/abstract_blockchain_functions.py
abstract_blockchain/abstract_blockchain_super_mgr.py
abstract_blockchain/abstract_contract_console.py
abstract_blockchain/abstract_contracts.py
abstract_blockchain/abstract_rpc_gui.py
abstract_blockchain/abstract_rpcs.py
abstract_blockchain/abstract_super_mgr.py
abstract_blockchain/abstract_w3_manager.py
abstract_blockchain/abstract_wallets.py
abstract_blockchain/abstract_webtool.py
abstract_blockchain/main.py
abstract_blockchain/new_contract.py
abstract_blockchain/rebuild.py
abstract_blockchain/rpc_functions.py
abstract_blockchain/speed_tyest.py
abstract_blockchain/test_rpc.py
abstract_blockchain/testabi.py
abstract_blockchain/data/__init__.py
abstract_blockchain/data/rpc_list.json
abstract_blockchain/data/text.py
abstract_blockchain/data/api_call_parameters/__init__.py
abstract_blockchain/data/api_call_parameters/allJs.json
abstract_blockchain/data/api_call_parameters/callTemplates.json
abstract_blockchain/data/api_call_parameters/callV.json
abstract_blockchain/data/api_call_parameters/callVars.json
abstract_blockchain/data/api_call_parameters/callVars2.json
abstract_blockchain/data/api_call_parameters/callsV.json
abstract_blockchain/data/api_call_parameters/prevInputs.json
abstract_blockchain/data/api_call_parameters/rpcVariables.json
abstract_contracts/__init__.py
abstract_contracts/parse_contract.py
abstract_contracts/pragma_versions.py
abstract_blockchain-0.0.2.32.dist-info/LICENSE.txt
abstract_blockchain-0.0.2.32.dist-info/METADATA
abstract_blockchain-0.0.2.32.dist-info/WHEEL
abstract_blockchain-0.0.2.32.dist-info/top_level.txt
abstract_blockchain-0.0.2.32.dist-info/RECORD
