Metadata-Version: 2.1
Name: abstract-blockchain
Version: 0.0.2.32
Summary: The Abstract Blockchain package provides a collection of modules designed to simplify interaction with blockchain networks, smart contracts, and related components. It offers tools for managing RPC parameters, working with smart contract ABIs, and facilitating user-friendly interactions through graphical user interfaces (GUIs).
Home-page: https://github.com/AbstractEndeavors/abstract_blockchain
Author: putkoff
Author-email: partners@abstractendeavors.com
Keywords: database,automation,API,testing,cryptography
Classifier: Development Status :: 3 - Alpha
Classifier: Intended Audience :: Developers
Classifier: License :: OSI Approved :: MIT License
Classifier: Operating System :: OS Independent
Classifier: Programming Language :: Python :: 3.11
Classifier: Topic :: Software Development
Classifier: Topic :: Utilities
Classifier: Intended Audience :: Financial and Insurance Industry
Requires-Python: >=3.6
License-File: LICENSE.txt
Requires-Dist: PySimpleGUI (>=4.60.5)
Requires-Dist: abstract-gui (>=0.0.62.03)
Requires-Dist: abstract-security (>=0.0.1)
Requires-Dist: abstract-utilities
Requires-Dist: abstract-webtools (>=0.1.5.4)
Requires-Dist: hexbytes (>=0.3.1)
Requires-Dist: requests (>=2.31.0)
Requires-Dist: web3 (>=6.9.0)
